[{"name":"Timestamp","value":2751.214833},{"name":"AudioHandlers","value":0},{"name":"Documents","value":18},{"name":"Frames","value":9},{"name":"JSEventListeners","value":107},{"name":"LayoutObjects","value":1563},{"name":"MediaKeySessions","value":0},{"name":"MediaKeys","value":0},{"name":"Nodes","value":2488},{"name":"Resources","value":21},{"name":"ContextLifecycleStateObservers","value":19},{"name":"V8PerContextDatas","value":1},{"name":"WorkerGlobalScopes","value":0},{"name":"UACSSResources","value":0},{"name":"RTCPeerConnections","value":0},{"name":"ResourceFetchers","value":18},{"name":"AdSubframes","value":0},{"name":"DetachedScriptStates","value":0},{"name":"ArrayBufferContents","value":2},{"name":"LayoutCount","value":12},{"name":"RecalcStyleCount","value":14},{"name":"LayoutDuration","value":0.051971},{"name":"RecalcStyleDuration","value":0.025437},{"name":"DevToolsCommandDuration","value":0.000543},{"name":"ScriptDuration","value":0.074505},{"name":"V8CompileDuration","value":0.000759},{"name":"TaskDuration","value":0.20259},{"name":"TaskOtherDuration","value":0.049375},{"name":"ThreadTime","value":0.16706},{"name":"ProcessTime","value":-0.01},{"name":"JSHeapUsedSize","value":4491740},{"name":"JSHeapTotalSize","value":7806976},{"name":"FirstMeaningfulPaint","value":0},{"name":"DomContentLoaded","value":2750.942229},{"name":"NavigationStart","value":2750.55362}]