[{"name":"Timestamp","value":2828.409414},{"name":"AudioHandlers","value":0},{"name":"Documents","value":17},{"name":"Frames","value":9},{"name":"JSEventListeners","value":88},{"name":"LayoutObjects","value":1481},{"name":"MediaKeySessions","value":0},{"name":"MediaKeys","value":0},{"name":"Nodes","value":2354},{"name":"Resources","value":20},{"name":"ContextLifecycleStateObservers","value":18},{"name":"V8PerContextDatas","value":1},{"name":"WorkerGlobalScopes","value":0},{"name":"UACSSResources","value":0},{"name":"RTCPeerConnections","value":0},{"name":"ResourceFetchers","value":17},{"name":"AdSubframes","value":0},{"name":"DetachedScriptStates","value":0},{"name":"ArrayBufferContents","value":1},{"name":"LayoutCount","value":12},{"name":"RecalcStyleCount","value":13},{"name":"LayoutDuration","value":0.039192},{"name":"RecalcStyleDuration","value":0.013855},{"name":"DevToolsCommandDuration","value":0.000508},{"name":"ScriptDuration","value":0.045453},{"name":"V8CompileDuration","value":0.000602},{"name":"TaskDuration","value":0.168133},{"name":"TaskOtherDuration","value":0.068523},{"name":"ThreadTime","value":0.129044},{"name":"ProcessTime","value":-0.01},{"name":"JSHeapUsedSize","value":3593752},{"name":"JSHeapTotalSize","value":7282688},{"name":"FirstMeaningfulPaint","value":0},{"name":"DomContentLoaded","value":2828.186233},{"name":"NavigationStart","value":2827.833642}]