[{"name":"Timestamp","value":2781.759062},{"name":"AudioHandlers","value":0},{"name":"Documents","value":22},{"name":"Frames","value":11},{"name":"JSEventListeners","value":123},{"name":"LayoutObjects","value":1576},{"name":"MediaKeySessions","value":0},{"name":"MediaKeys","value":0},{"name":"Nodes","value":2592},{"name":"Resources","value":22},{"name":"ContextLifecycleStateObservers","value":23},{"name":"V8PerContextDatas","value":1},{"name":"WorkerGlobalScopes","value":0},{"name":"UACSSResources","value":0},{"name":"RTCPeerConnections","value":0},{"name":"ResourceFetchers","value":22},{"name":"AdSubframes","value":0},{"name":"DetachedScriptStates","value":0},{"name":"ArrayBufferContents","value":3},{"name":"LayoutCount","value":13},{"name":"RecalcStyleCount","value":17},{"name":"LayoutDuration","value":0.047602},{"name":"RecalcStyleDuration","value":0.024269},{"name":"DevToolsCommandDuration","value":0.001737},{"name":"ScriptDuration","value":0.092837},{"name":"V8CompileDuration","value":0.001012},{"name":"TaskDuration","value":0.260771},{"name":"TaskOtherDuration","value":0.093314},{"name":"ThreadTime","value":0.224433},{"name":"ProcessTime","value":-0.01},{"name":"JSHeapUsedSize","value":9166772},{"name":"JSHeapTotalSize","value":14815232},{"name":"FirstMeaningfulPaint","value":2776.585488},{"name":"DomContentLoaded","value":2776.523196},{"name":"NavigationStart","value":2776.198607}]